orchestrator_service_rules
