Metadata-Version: 2.1
Name: orchestrator-service-rules
Version: 0.4
Summary: orchestrator for code execution through a rule
Author: Daniel Garcia Uscanga
Author-email: daniel.garcia@tangelolatam.com
License-File: LICENSE.txt
